{
  "rubber": [
    {
      "name": "Songkhla",
      "price": [
        "53.73",
        "53.23",
        "51.63",
        "-",
        "-"
      ],
      "volume": [
        "9,055",
        "8,870",
        "10,190",
        "-",
        "-"
      ]
    },
    {
      "name": "Suratthani",
      "price": [
        "54.73",
        "54.23",
        "52.40",
        "-",
        "-"
      ],
      "volume": [
        "22,000",
        "16,000",
        "-",
        "-",
        "-"
      ]
    },
    {
      "name": "NakornSrithammarat",
      "price": [
        "53.73",
        "52.73",
        "-",
        "-",
        "-"
      ],
      "volume": [
        "5,878",
        "244",
        "-",
        "-",
        "-"
      ]
    },
    {
      "name": "Yala",
      "price": [
        "51.50",
        "51.50",
        "51.50",
        "49.09",
        "45.93"
      ],
      "volume": [
        "-",
        "-",
        "1,350",
        "228",
        "-"
      ]
    },
    {
      "name": "Burirum",
      "price": [
        "-",
        "-",
        "-",
        "-",
        "-"
      ],
      "volume": [
        "-",
        "-",
        "-",
        "-",
        "-"
      ]
    },
    {
      "name": "Nongkhai",
      "price": [
        "-",
        "-",
        "-",
        "-",
        "-"
      ],
      "volume": [
        "-",
        "-",
        "-",
        "-",
        "-"
      ]
    }
  ],
  "rubber_smoke": [
    {
      "name": "Songkhla",
      "price": [
        "54.29",
        "53.88",
        "53.45",
        "53.66",
        "45.67"
      ],
      "volume": "136,995"
    },
    {
      "name": "Suratthani",
      "price": [
        "54.34",
        "53.14",
        "52.14",
        "51.14",
        "50.14"
      ],
      "volume": "57,000"
    },
    {
      "name": "NakornSrithammarat",
      "price": [
        "54.42",
        "54.26",
        "53.45",
        "53.86",
        "48.93"
      ],
      "volume": "172,000"
    },
    {
      "name": "Yala",
      "price": [
        "-",
        "-",
        "-",
        "-",
        "-"
      ],
      "volume": "-"
    },
    {
      "name": "Burirum",
      "price": [
        "-",
        "-",
        "-",
        "-",
        "-"
      ],
      "volume": "-"
    },
    {
      "name": "Nongkhai",
      "price": [
        "-",
        "-",
        "-",
        "-",
        "-"
      ],
      "volume": "-"
    }
  ]
}